ezphot/__init__.py
ezphot/configuration/__init__.py
ezphot/configuration/configuration.py
ezphot/configuration/common/CCD.dat
ezphot/configuration/common/calibdata.config
ezphot/configuration/common/catalog.config
ezphot/configuration/common/obs_location.txt
ezphot/configuration/common/obsdata.config
ezphot/configuration/common/observatory.config
ezphot/configuration/common/psfex.config
ezphot/configuration/common/refdata.config
ezphot/configuration/common/scamp.config
ezphot/configuration/common/scidata.config
ezphot/configuration/common/sdtdata.config
ezphot/configuration/common/sex.config
ezphot/configuration/common/swarp.config
ezphot/configuration/common/psfex/default.psfexconfig
ezphot/configuration/common/psfex/psfex.xml
ezphot/configuration/common/scamp/default.scampconfig
ezphot/configuration/common/scamp/result/scamp.xml
ezphot/configuration/common/sextractor/7DT_C361K_HIGH_1x1.astrometry.sexconfig
ezphot/configuration/common/sextractor/7DT_C361K_HIGH_1x1.psfex.sexconfig
ezphot/configuration/common/sextractor/7DT_C361K_HIGH_1x1.scamp.sexconfig
ezphot/configuration/common/sextractor/7DT_C361K_HIGH_1x1.sexconfig
ezphot/configuration/common/sextractor/7DT_C361K_HIGH_2x2.astrometry.sexconfig
ezphot/configuration/common/sextractor/7DT_C361K_HIGH_2x2.psfex.sexconfig
ezphot/configuration/common/sextractor/7DT_C361K_HIGH_2x2.scamp.sexconfig
ezphot/configuration/common/sextractor/7DT_C361K_HIGH_2x2.sexconfig
ezphot/configuration/common/sextractor/7DT_C361K_LOW_1x1.astrometry.sexconfig
ezphot/configuration/common/sextractor/7DT_C361K_LOW_1x1.psfex.sexconfig
ezphot/configuration/common/sextractor/7DT_C361K_LOW_1x1.scamp.sexconfig
ezphot/configuration/common/sextractor/7DT_C361K_LOW_1x1.sexconfig
ezphot/configuration/common/sextractor/7DT_C361K_LOW_2x2.astrometry.sexconfig
ezphot/configuration/common/sextractor/7DT_C361K_LOW_2x2.psfex.sexconfig
ezphot/configuration/common/sextractor/7DT_C361K_LOW_2x2.scamp.sexconfig
ezphot-0.2.3.dist-info/licenses/LICENSE
ezphot-0.2.3.dist-info/METADATA
ezphot-0.2.3.dist-info/WHEEL
ezphot-0.2.3.dist-info/top_level.txt
ezphot-0.2.3.dist-info/RECORD
